nistitl.py
nistitl-0.5.dist-info/AUTHORS.rst
nistitl-0.5.dist-info/LICENSE
nistitl-0.5.dist-info/METADATA
nistitl-0.5.dist-info/WHEEL
nistitl-0.5.dist-info/top_level.txt
nistitl-0.5.dist-info/RECORD
