Metadata-Version: 2.1
Name: nistitl
Version: 0.5
Summary: NIST-ITL Python Parsing Library
Home-page: https://github.com/idemia/python-nistitl
Author: Olivier Heurtier
Author-email: olivier.heurtier@idemia.com
License: CeCILL-C
Platform: UNKNOWN
Classifier: Development Status :: 4 - Beta
Classifier: Programming Language :: Python :: 3.6
Classifier: Programming Language :: Python :: 3.7
Classifier: Programming Language :: Python :: 3.8
Classifier: Programming Language :: Python :: 3.9
Classifier: Programming Language :: Python :: 3.10
Classifier: License :: CeCILL-C Free Software License Agreement (CECILL-C)
Classifier: Operating System :: OS Independent
License-File: LICENSE
License-File: AUTHORS.rst
